{
    "key": "group_657ac14abe3a2",
    "title": "Slots Data",
    "fields": [
        {
            "key": "field_657ac2ecb8544",
            "label": "Slots Information",
            "name": "",
            "aria-label": "",
            "type": "tab",
            "instructions": "",
            "required": 0,
            "conditional_logic": 0,
            "wrapper": {
                "width": "",
                "class": "",
                "id": ""
            },
            "readonly": 0,
            "placement": "top",
            "endpoint": 0
        },
        {
            "key": "field_657ac14b078eb",
            "label": "Slot Title",
            "name": "slot_title",
            "aria-label": "",
            "type": "text",
            "instructions": "",
            "required": 0,
            "conditional_logic": 0,
            "wrapper": {
                "width": "25",
                "class": "",
                "id": ""
            },
            "readonly": 1,
            "default_value": "",
            "translations": "sync",
            "maxlength": "",
            "placeholder": "",
            "prepend": "",
            "append": ""
        },
        {
            "key": "field_657ac14b07974",
            "label": "Slot Slug",
            "name": "id_slug",
            "aria-label": "",
            "type": "text",
            "instructions": "",
            "required": 0,
            "conditional_logic": 0,
            "wrapper": {
                "width": "25",
                "class": "",
                "id": ""
            },
            "readonly": 1,
            "default_value": "",
            "translations": "sync",
            "maxlength": "",
            "placeholder": "",
            "prepend": "",
            "append": ""
        },
        {
            "key": "field_657ac14b079f8",
            "label": "Provider",
            "name": "provider",
            "aria-label": "",
            "type": "text",
            "instructions": "",
            "required": 0,
            "conditional_logic": 0,
            "wrapper": {
                "width": "25",
                "class": "",
                "id": ""
            },
            "readonly": 1,
            "default_value": "",
            "translations": "sync",
            "maxlength": "",
            "placeholder": "",
            "prepend": "",
            "append": ""
        },
        {
            "key": "field_657ac14b07a6f",
            "label": "Provider ID",
            "name": "provider_id",
            "aria-label": "",
            "type": "text",
            "instructions": "",
            "required": 0,
            "conditional_logic": 0,
            "wrapper": {
                "width": "25",
                "class": "",
                "id": ""
            },
            "readonly": 1,
            "default_value": "",
            "translations": "sync",
            "maxlength": "",
            "placeholder": "",
            "prepend": "",
            "append": ""
        },
        {
            "key": "field_657ac860b2aa2",
            "label": "Technology",
            "name": "technology",
            "aria-label": "",
            "type": "text",
            "instructions": "",
            "required": 0,
            "conditional_logic": 0,
            "wrapper": {
                "width": "33",
                "class": "",
                "id": ""
            },
            "readonly": 1,
            "default_value": "",
            "translations": "translate",
            "maxlength": "",
            "placeholder": "",
            "prepend": "",
            "append": ""
        },
        {
            "key": "field_657ae8893a84e",
            "label": "Devices",
            "name": "devices",
            "aria-label": "",
            "type": "text",
            "instructions": "",
            "required": 0,
            "conditional_logic": 0,
            "wrapper": {
                "width": "33",
                "class": "",
                "id": ""
            },
            "readonly": 1,
            "default_value": "",
            "translations": "translate",
            "maxlength": "",
            "placeholder": "",
            "prepend": "",
            "append": ""
        },
        {
            "key": "field_657ac87eb2aa3",
            "label": "Release Date",
            "name": "release_date",
            "aria-label": "",
            "type": "text",
            "instructions": "",
            "required": 0,
            "conditional_logic": 0,
            "wrapper": {
                "width": "33",
                "class": "",
                "id": ""
            },
            "readonly": 1,
            "default_value": "",
            "translations": "translate",
            "maxlength": "",
            "placeholder": "",
            "prepend": "",
            "append": ""
        },
        {
            "key": "field_657ac9cfe45c9",
            "label": "Slot Offline on Desktop",
            "name": "temporarily_offline",
            "aria-label": "",
            "type": "text",
            "instructions": "",
            "required": 0,
            "conditional_logic": 0,
            "wrapper": {
                "width": "25",
                "class": "",
                "id": ""
            },
            "readonly": 1,
            "default_value": "",
            "translations": "sync",
            "maxlength": "",
            "placeholder": "",
            "prepend": "",
            "append": ""
        },
        {
            "key": "field_657ac9e9e45ca",
            "label": "Slot Offline on Mobile",
            "name": "temporarily_offline_mobile",
            "aria-label": "",
            "type": "text",
            "instructions": "",
            "required": 0,
            "conditional_logic": 0,
            "wrapper": {
                "width": "25",
                "class": "",
                "id": ""
            },
            "readonly": 1,
            "default_value": "",
            "translations": "sync",
            "maxlength": "",
            "placeholder": "",
            "prepend": "",
            "append": ""
        },
        {
            "key": "field_657b250a39190",
            "label": "Rating",
            "name": "rating",
            "aria-label": "",
            "type": "radio",
            "instructions": "",
            "required": 0,
            "conditional_logic": 0,
            "wrapper": {
                "width": "25",
                "class": "",
                "id": ""
            },
            "readonly": 0,
            "choices": {
                "1": "1",
                "2": "2",
                "3": "3",
                "4": "4",
                "5": "5",
                "6": "6",
                "7": "7",
                "8": "8",
                "9": "9",
                "10": "10"
            },
            "default_value": "",
            "return_format": "value",
            "translations": "sync",
            "allow_null": 0,
            "other_choice": 0,
            "layout": "horizontal",
            "save_other_choice": 0
        },
        {
            "key": "field_657ac14b07ae1",
            "label": "Slot Image",
            "name": "slot_image",
            "aria-label": "",
            "type": "image",
            "instructions": "",
            "required": 0,
            "conditional_logic": 0,
            "wrapper": {
                "width": "25",
                "class": "",
                "id": ""
            },
            "readonly": 0,
            "return_format": "array",
            "library": "all",
            "min_width": "",
            "min_height": "",
            "min_size": "",
            "max_width": "",
            "max_height": "",
            "max_size": "",
            "mime_types": "",
            "preview_size": "medium"
        },
        {
            "key": "field_657ac14b07b5c",
            "label": "RtP",
            "name": "",
            "aria-label": "",
            "type": "tab",
            "instructions": "",
            "required": 0,
            "conditional_logic": 0,
            "wrapper": {
                "width": "",
                "class": "",
                "id": ""
            },
            "readonly": 1,
            "placement": "top",
            "endpoint": 0
        },
        {
            "key": "field_657ac14b07ba0",
            "label": "RtP",
            "name": "Rtp",
            "aria-label": "",
            "type": "text",
            "instructions": "",
            "required": 0,
            "conditional_logic": 0,
            "wrapper": {
                "width": "25",
                "class": "",
                "id": ""
            },
            "readonly": 1,
            "default_value": "",
            "translations": "translate",
            "maxlength": "",
            "placeholder": "",
            "prepend": "",
            "append": ""
        },
        {
            "key": "field_657ac14b07bde",
            "label": "RtP Variable",
            "name": "Rtp_variable",
            "aria-label": "",
            "type": "text",
            "instructions": "",
            "required": 0,
            "conditional_logic": 0,
            "wrapper": {
                "width": "25",
                "class": "",
                "id": ""
            },
            "readonly": 1,
            "default_value": "",
            "translations": "translate",
            "maxlength": "",
            "placeholder": "",
            "prepend": "",
            "append": ""
        },
        {
            "key": "field_657ac14b07c1c",
            "label": "RtP Variable Max",
            "name": "Rtp_variable_max",
            "aria-label": "",
            "type": "text",
            "instructions": "",
            "required": 0,
            "conditional_logic": 0,
            "wrapper": {
                "width": "25",
                "class": "",
                "id": ""
            },
            "readonly": 1,
            "default_value": "",
            "translations": "translate",
            "maxlength": "",
            "placeholder": "",
            "prepend": "",
            "append": ""
        },
        {
            "key": "field_657ac14b07c59",
            "label": "RtP Variable Min",
            "name": "Rtp_variable_min",
            "aria-label": "",
            "type": "text",
            "instructions": "",
            "required": 0,
            "conditional_logic": 0,
            "wrapper": {
                "width": "25",
                "class": "",
                "id": ""
            },
            "readonly": 1,
            "default_value": "",
            "translations": "translate",
            "maxlength": "",
            "placeholder": "",
            "prepend": "",
            "append": ""
        },
        {
            "key": "field_657ac73679015",
            "label": "Variance",
            "name": "variance",
            "aria-label": "",
            "type": "text",
            "instructions": "",
            "required": 0,
            "conditional_logic": 0,
            "wrapper": {
                "width": "25",
                "class": "",
                "id": ""
            },
            "readonly": 1,
            "default_value": "",
            "translations": "translate",
            "maxlength": "",
            "placeholder": "",
            "prepend": "",
            "append": ""
        },
        {
            "key": "field_657ac74a79016",
            "label": "Max Coin Win",
            "name": "max_coin_win",
            "aria-label": "",
            "type": "text",
            "instructions": "",
            "required": 0,
            "conditional_logic": 0,
            "wrapper": {
                "width": "25",
                "class": "",
                "id": ""
            },
            "readonly": 1,
            "default_value": "",
            "translations": "translate",
            "maxlength": "",
            "placeholder": "",
            "prepend": "",
            "append": ""
        },
        {
            "key": "field_657ac76179017",
            "label": "Min Bet",
            "name": "min_bet",
            "aria-label": "",
            "type": "text",
            "instructions": "",
            "required": 0,
            "conditional_logic": 0,
            "wrapper": {
                "width": "25",
                "class": "",
                "id": ""
            },
            "readonly": 1,
            "default_value": "",
            "translations": "translate",
            "maxlength": "",
            "placeholder": "",
            "prepend": "",
            "append": ""
        },
        {
            "key": "field_657ac76d79018",
            "label": "Max Bet",
            "name": "max_bet",
            "aria-label": "",
            "type": "text",
            "instructions": "",
            "required": 0,
            "conditional_logic": 0,
            "wrapper": {
                "width": "25",
                "class": "",
                "id": ""
            },
            "readonly": 1,
            "default_value": "",
            "translations": "translate",
            "maxlength": "",
            "placeholder": "",
            "prepend": "",
            "append": ""
        },
        {
            "key": "field_657ac826b2aa0",
            "label": "Lines",
            "name": "lines",
            "aria-label": "",
            "type": "text",
            "instructions": "",
            "required": 0,
            "conditional_logic": 0,
            "wrapper": {
                "width": "25",
                "class": "",
                "id": ""
            },
            "readonly": 1,
            "default_value": "",
            "translations": "translate",
            "maxlength": "",
            "placeholder": "",
            "prepend": "",
            "append": ""
        },
        {
            "key": "field_657ac83fb2aa1",
            "label": "Reels Rows",
            "name": "reels_rows",
            "aria-label": "",
            "type": "text",
            "instructions": "",
            "required": 0,
            "conditional_logic": 0,
            "wrapper": {
                "width": "25",
                "class": "",
                "id": ""
            },
            "readonly": 1,
            "default_value": "",
            "translations": "translate",
            "maxlength": "",
            "placeholder": "",
            "prepend": "",
            "append": ""
        },
        {
            "key": "field_657ac59c7dc9c",
            "label": "iFrame",
            "name": "",
            "aria-label": "",
            "type": "tab",
            "instructions": "",
            "required": 0,
            "conditional_logic": 0,
            "wrapper": {
                "width": "",
                "class": "",
                "id": ""
            },
            "readonly": 0,
            "placement": "top",
            "endpoint": 0
        },
        {
            "key": "field_657ac5b37dc9d",
            "label": "Fallback iFrame",
            "name": "fallback_iframe",
            "aria-label": "",
            "type": "textarea",
            "instructions": "",
            "required": 0,
            "conditional_logic": 0,
            "wrapper": {
                "width": "50",
                "class": "",
                "id": ""
            },
            "readonly": 1,
            "default_value": "",
            "maxlength": "",
            "rows": "",
            "placeholder": "",
            "new_lines": ""
        },
        {
            "key": "field_657ac5d07dc9e",
            "label": "Fallback Mobile iFrame",
            "name": "fallback_mobile_iframe",
            "aria-label": "",
            "type": "textarea",
            "instructions": "",
            "required": 0,
            "conditional_logic": 0,
            "wrapper": {
                "width": "50",
                "class": "",
                "id": ""
            },
            "readonly": 1,
            "default_value": "",
            "translations": "translate",
            "maxlength": "",
            "rows": "",
            "placeholder": "",
            "new_lines": ""
        },
        {
            "key": "field_657ac63814aea",
            "label": "Width",
            "name": "width",
            "aria-label": "",
            "type": "text",
            "instructions": "",
            "required": 0,
            "conditional_logic": 0,
            "wrapper": {
                "width": "25",
                "class": "",
                "id": ""
            },
            "readonly": 1,
            "default_value": "",
            "translations": "translate",
            "maxlength": "",
            "placeholder": "",
            "prepend": "",
            "append": ""
        },
        {
            "key": "field_657ac65a14aeb",
            "label": "Height",
            "name": "height",
            "aria-label": "",
            "type": "text",
            "instructions": "",
            "required": 0,
            "conditional_logic": 0,
            "wrapper": {
                "width": "25",
                "class": "",
                "id": ""
            },
            "readonly": 1,
            "default_value": "",
            "translations": "translate",
            "maxlength": "",
            "placeholder": "",
            "prepend": "",
            "append": ""
        },
        {
            "key": "field_657ac6f6adca3",
            "label": "Layout",
            "name": "layout",
            "aria-label": "",
            "type": "text",
            "instructions": "",
            "required": 0,
            "conditional_logic": 0,
            "wrapper": {
                "width": "25",
                "class": "",
                "id": ""
            },
            "readonly": 1,
            "default_value": "",
            "translations": "translate",
            "maxlength": "",
            "placeholder": "",
            "prepend": "",
            "append": ""
        },
        {
            "key": "field_657ac6a714aec",
            "label": "Has Mobile",
            "name": "default_force_landscape",
            "aria-label": "",
            "type": "text",
            "instructions": "",
            "required": 0,
            "conditional_logic": 0,
            "wrapper": {
                "width": "25",
                "class": "",
                "id": ""
            },
            "readonly": 1,
            "default_value": "",
            "translations": "translate",
            "maxlength": "",
            "placeholder": "",
            "prepend": "",
            "append": ""
        },
        {
            "key": "field_65bb589428460",
            "label": "Metrics",
            "name": "",
            "aria-label": "",
            "type": "tab",
            "instructions": "",
            "required": 0,
            "conditional_logic": 0,
            "wrapper": {
                "width": "",
                "class": "",
                "id": ""
            },
            "readonly": 0,
            "placement": "top",
            "endpoint": 0
        },
        {
            "key": "field_65bb591f820aa",
            "label": "Total Likes",
            "name": "total_likes",
            "aria-label": "",
            "type": "text",
            "instructions": "",
            "required": 0,
            "conditional_logic": 0,
            "wrapper": {
                "width": "50",
                "class": "",
                "id": ""
            },
            "readonly": 1,
            "default_value": "",
            "maxlength": "",
            "placeholder": "",
            "prepend": "",
            "append": ""
        },
        {
            "key": "field_65bb5ee71dba0",
            "label": "Play Count",
            "name": "play_count",
            "aria-label": "",
            "type": "text",
            "instructions": "",
            "required": 0,
            "conditional_logic": 0,
            "wrapper": {
                "width": "50",
                "class": "",
                "id": ""
            },
            "readonly": 1,
            "default_value": "",
            "maxlength": "",
            "placeholder": "",
            "prepend": "",
            "append": ""
        }
    ],
    "location": [
        [
            {
                "param": "post_type",
                "operator": "==",
                "value": "slots"
            }
        ]
    ],
    "menu_order": 0,
    "position": "normal",
    "style": "default",
    "label_placement": "top",
    "instruction_placement": "label",
    "hide_on_screen": "",
    "active": true,
    "description": "",
    "show_in_rest": 0,
    "modified": 1708082366
}
